NOTICE
passpy/__init__.py
passpy/__main__.py
passpy/exceptions.py
passpy/git.py
passpy/gpg.py
passpy/store.py
passpy/util.py
passpy-1.0.2.dist-info/entry_points.txt
passpy-1.0.2.dist-info/LICENSE
passpy-1.0.2.dist-info/WHEEL
passpy-1.0.2.dist-info/METADATA
passpy-1.0.2.dist-info/RECORD
