Metadata-Version: 2.1
Name: passpy
Version: 1.0.2
Summary: ZX2C4's pass compatible Python library and cli
Home-page: https://github.com/bfrascher/passpy
License: GPL-3.0-or-later
Author: Benedikt Rascher-Friesenhausen
Author-email: benedikt_rascher-friesenhausen+passpy@gmail.com
Requires-Python: >=3.3
Classifier: Development Status :: 5 - Production/Stable
Classifier: Environment :: Console
Classifier: Intended Audience :: Developers
Classifier: Intended Audience :: End Users/Desktop
Classifier: License :: OSI Approved :: GNU General Public License v3 (GPLv3)
Classifier: License :: OSI Approved :: GNU General Public License v3 or later (GPLv3+)
Classifier: Operating System :: MacOS
Classifier: Operating System :: Microsoft :: Windows
Classifier: Operating System :: POSIX :: Linux
Classifier: Programming Language :: Python :: 3
Classifier: Programming Language :: Python :: 3.4
Classifier: Programming Language :: Python :: 3.5
Classifier: Programming Language :: Python :: 3.6
Classifier: Programming Language :: Python :: 3.7
Classifier: Programming Language :: Python :: 3.8
Classifier: Topic :: Utilities
Provides-Extra: color
Requires-Dist: GitPython (>=1.0.1)
Requires-Dist: click (>=2.0)
Requires-Dist: colorama (>=0.3); extra == "color"
Requires-Dist: pyperclip (>=1.5)
Requires-Dist: python-gnupg (>=0.3.8)
Project-URL: Documentation, https://passpy.readthedocs.io/en/latest/index.html
Project-URL: Repository, https://github.com/bfrascher/passpy
